{"final_weight_diff": 2389.482421875, "final_feature_diff": 77.27354451056644, "best_weight_diff": 2389.5126953125, "best_feature_diff": 77.28193431174836, "num_feature_traj": 218, "num_feature_timesteps": "100692", "final_test_returns": 1441.8380263913575, "final_test_normalized_returns": 44.92480714424802, "best_return": 1576.7230241410855, "best_return_normalized": 49.06928405577659, "convergence_step": "10000", "convergence_iter": "2", "best_step": "95000", "best_iter": "19", "best_5percent_normalized": 49.06928405577659, "best_10percent_normalized": 48.40541177892085, "best_25percent_normalized": 46.20625647549195, "best_50percent_normalized": 40.67927856630979, "best_100percent_normalized": 27.768836925304708, "best_later_half_normalized": 38.61659892551918, "best_last_four_normalized": 39.54220972536535}