{
    "final_weight_diff": 0.00020224654872436076,
    "final_weight_sim": 0.8600236177444458,
    "final_feature_diff": 0.6089325056927797,
    "final_feature_sim": 0.6661176650145445,
    "final_0_weight_diff": 0.0025502697099000216,
    "final_1_weight_diff": 0.0023807440884411335,
    "final_2_weight_diff": 0.002417003270238638,
    "final_0_weight_sim": 1.0,
    "final_1_weight_sim": 1.0,
    "final_2_weight_sim": 0.9999999403953552,
    "best_weight_diff": 7.732476660748944e-05,
    "best_weight_sim": 0.9362207651138306,
    "best_feature_diff": 0.40079092990962,
    "best_feature_sim": 0.778071496606903,
    "best_0_weight_diff": 0.0009704353287816048,
    "best_1_weight_diff": 0.0008892504265531898,
    "best_2_weight_diff": 0.0009494057158008218,
    "best_0_weight_sim": 0.9999998211860657,
    "best_1_weight_sim": 1.0,
    "best_2_weight_sim": 1.0,
    "num_feature_traj": 54,
    "num_feature_timesteps": "12717",
    "final_test_returns": 2838.768551866909,
    "final_test_normalized_returns": 61.80228443317093,
    "best_return": 3454.601996169833,
    "best_return_normalized": 75.21717400761689,
    "convergence_step": "5000",
    "convergence_iter": "1",
    "best_step": "20000",
    "best_iter": "4"
}