{"final_weight_diff": 311.5582580566406, "final_feature_diff": 34.45854594124636, "best_weight_diff": 306.9583740234375, "best_feature_diff": 33.68586169898202, "num_feature_traj": 20, "num_feature_timesteps": "20000", "final_test_returns": 4659.536554703127, "final_test_normalized_returns": 39.78771088522647, "best_return": 4935.442973377054, "best_return_normalized": 42.01004227262268, "convergence_step": "5000", "convergence_iter": "1", "best_step": "55000", "best_iter": "11", "best_5percent_normalized": 42.01004227262268, "best_10percent_normalized": 41.96850242358279, "best_25percent_normalized": 41.53277128497236, "best_50percent_normalized": 41.021391218203824, "best_100percent_normalized": 37.847954161753314, "best_later_half_normalized": 39.540508686092586, "best_last_four_normalized": 40.504417211594046}