{
    "final_weight_diff": 0.0014471739996224642,
    "final_weight_sim": 0.740526556968689,
    "final_feature_diff": 0.4148652576425709,
    "final_feature_sim": 0.5894397519604222,
    "final_0_weight_diff": 0.001645434182137251,
    "final_1_weight_diff": 0.00151798315346241,
    "final_2_weight_diff": 0.001167859765700996,
    "final_0_weight_sim": 0.7112045288085938,
    "final_1_weight_sim": 0.7336918115615845,
    "final_2_weight_sim": 0.7559574842453003,
    "best_weight_diff": 0.0011437870562076569,
    "best_weight_sim": 0.7891059517860413,
    "best_feature_diff": 0.394416958136444,
    "best_feature_sim": 0.6232886436587752,
    "best_0_weight_diff": 0.0013301002327352762,
    "best_1_weight_diff": 0.001191086252219975,
    "best_2_weight_diff": 0.0009055272676050663,
    "best_0_weight_sim": 0.7629290223121643,
    "best_1_weight_sim": 0.7824667692184448,
    "best_2_weight_sim": 0.80279940366745,
    "num_feature_traj": 20,
    "num_feature_timesteps": "20000",
    "final_test_returns": 4716.784495700862,
    "final_test_normalized_returns": 40.24882337675364,
    "best_return": 4951.841128370363,
    "best_return_normalized": 42.1421237758808,
    "convergence_step": "20000",
    "convergence_iter": "4",
    "best_step": "70000",
    "best_iter": "14"
}