{"final_weight_diff": 37.211673736572266, "final_feature_diff": 7.257491642927751, "best_weight_diff": 28.88566780090332, "best_feature_diff": 6.303497165136235, "num_feature_traj": 2, "num_feature_timesteps": "2000", "final_test_returns": 2681.2426847425854, "final_test_normalized_returns": 23.85323360181601, "best_return": 3180.3062762277877, "best_return_normalized": 27.87301932842133, "convergence_step": "5000", "convergence_iter": "1", "best_step": "35000", "best_iter": "7", "best_5percent_normalized": 27.87301932842133, "best_10percent_normalized": 26.885719203527145, "best_25percent_normalized": 25.235391629817933, "best_50percent_normalized": 24.189681659441263, "best_100percent_normalized": 21.16218624562723, "best_later_half_normalized": 21.697086594437717}