{"final_weight_diff": 38.53007507324219, "final_feature_diff": 8.63588915077683, "best_weight_diff": 22.13839340209961, "best_feature_diff": 6.706261147479353, "num_feature_traj": 27, "num_feature_timesteps": "6901", "final_test_returns": 1257.3759216888914, "final_test_normalized_returns": 27.354321751160928, "best_return": 3098.2244205317907, "best_return_normalized": 67.45409152448777, "convergence_step": "5000", "convergence_iter": "1", "best_step": "15000", "best_iter": "3", "best_5percent_normalized": 67.45409152448777, "best_10percent_normalized": 65.70405876173736, "best_25percent_normalized": 62.79453154602155, "best_50percent_normalized": 54.40943653912852, "best_100percent_normalized": 37.685289040369206, "best_later_half_normalized": 38.43707814806865}