{"final_weight_diff": 303.5596923828125, "final_feature_diff": 38.719184681077024, "best_weight_diff": 300.66082763671875, "best_feature_diff": 37.86447886713614, "num_feature_traj": 218, "num_feature_timesteps": "100692", "final_test_returns": 2098.898176324423, "final_test_normalized_returns": 65.11363960385027, "best_return": 2296.016232191618, "best_return_normalized": 71.17028967625342, "convergence_step": "5000", "convergence_iter": "1", "best_step": "45000", "best_iter": "9", "best_5percent_normalized": 71.17028967625342, "best_10percent_normalized": 70.87743722804262, "best_25percent_normalized": 69.37272764824635, "best_50percent_normalized": 65.99030519104502, "best_100percent_normalized": 59.88429130582328, "best_later_half_normalized": 62.04902043214524, "best_last_four_normalized": 63.917387854839106}