{
    "final_weight_diff": 0.00016089811106212437,
    "final_weight_sim": 0.8796281218528748,
    "final_feature_diff": 0.6771172177221026,
    "final_feature_sim": 0.6739793303290005,
    "final_0_weight_diff": 0.0022567491978406906,
    "final_1_weight_diff": 0.0019214783096686006,
    "final_2_weight_diff": 0.0016677463427186012,
    "final_0_weight_sim": 1.0,
    "final_1_weight_sim": 1.0,
    "final_2_weight_sim": 1.0,
    "best_weight_diff": 0.0001467571419198066,
    "best_weight_sim": 0.8882878422737122,
    "best_feature_diff": 0.653069578259484,
    "best_feature_sim": 0.6863165038348374,
    "best_0_weight_diff": 0.002050454495474696,
    "best_1_weight_diff": 0.001745843794196844,
    "best_2_weight_diff": 0.001535645336844027,
    "best_0_weight_sim": 1.0000001192092896,
    "best_1_weight_sim": 1.0000001192092896,
    "best_2_weight_sim": 0.9999998211860657,
    "num_feature_traj": 89,
    "num_feature_timesteps": "77552",
    "final_test_returns": 3276.3666593131243,
    "final_test_normalized_returns": 71.33461877402875,
    "best_return": 3544.361400695925,
    "best_return_normalized": 77.17243075946239,
    "convergence_step": "5000",
    "convergence_iter": "1",
    "best_step": "85000",
    "best_iter": "17"
}