{
    "final_weight_diff": 73.2171401977539,
    "final_feature_diff": 28.152125850212244,
    "best_weight_diff": 53.98917007446289,
    "best_feature_diff": 27.456677666375054,
    "num_feature_traj": 20,
    "num_feature_timesteps": "20000",
    "final_test_returns": 7363.689371771354,
    "final_test_normalized_returns": 61.568732546737,
    "best_return": 8149.120304720837,
    "best_return_normalized": 67.895108798927,
    "convergence_step": "5000",
    "convergence_iter": "1",
    "best_step": "50000",
    "best_iter": "10"
}